echidna2022/__init__.py
echidna2022-0.0.1.dist-info/METADATA
echidna2022-0.0.1.dist-info/WHEEL
echidna2022-0.0.1.dist-info/top_level.txt
echidna2022-0.0.1.dist-info/RECORD
