Metadata-Version: 2.1
Name: echidna2022
Version: 0.0.1
Summary: BOT and CLI framework for handling multiple services in python
Home-page: https://github.com/1ntegrale9/echidna
Author: 1ntegrale9
Author-email: 1ntegrale9uation@gmail.com
License: UNKNOWN
Platform: UNKNOWN
Classifier: Programming Language :: Python :: 3.7
Classifier: License :: OSI Approved :: MIT License
Classifier: Operating System :: OS Independent
